<wpml-config>
    <custom-fields>
        <custom-field action="translate">_layout</custom-field>
        <custom-field action="copy">_breadcrumb</custom-field>
        <custom-field action="copy">_sticky_footer</custom-field>

        <custom-field action="translate">_sidebar</custom-field>
        <custom-field action="translate">_introduce</custom-field>
        <custom-field action="translate">_introduce_text_type</custom-field>
        <custom-field action="translate">_custom_title</custom-field>
        <custom-field action="translate">_custom_introduce_text</custom-field>
        <custom-field action="translate">_slideshow_category</custom-field>
        <custom-field action="translate">_slideshow_number</custom-field>
        <custom-field action="translate">__slideshow_type</custom-field>
        <custom-field action="translate">_slideshow_rev</custom-field>
        <custom-field action="copy">_feature_title_color</custom-field>
        <custom-field action="copy">_feature_introduce_color</custom-field>
        <custom-field action="copy">_introduce_background_color</custom-field>
        <custom-field action="copy">_feature_background_image</custom-field>
        <custom-field action="copy">_feature_background_position_x</custom-field>
        <custom-field action="copy">_feature_background_position_y</custom-field>
        <custom-field action="copy">_feature_background_repeat</custom-field>
        <custom-field action="copy">_feature_background_attachment</custom-field>
        <custom-field action="copy">_feature_background_size</custom-field>

        <custom-field action="copy">_page_background_color</custom-field>
        <custom-field action="copy">_page_background_image</custom-field>
        <custom-field action="copy">_page_background_position_x</custom-field>
        <custom-field action="copy">_page_background_position_y</custom-field>
        <custom-field action="copy">_page_background_repeat</custom-field>
        <custom-field action="copy">_page_background_attachment</custom-field>
        <custom-field action="copy">_page_background_size</custom-field>
        <custom-field action="copy">_page_inner_background_color</custom-field>
        <custom-field action="copy">_page_color</custom-field>
        
        <custom-field action="copy">_footer_background_color</custom-field>
        <custom-field action="copy">_footer_color</custom-field>
        <custom-field action="copy">_footer_title_color</custom-field>
        <custom-field action="translate">_custom_css</custom-field>
        <custom-field action="translate">_custom_js</custom-field>

        <custom-field action="translate">_featured_image</custom-field>
        <custom-field action="copy">_type</custom-field>
        <custom-field action="translate">_breadcrumbs_page</custom-field>
        <custom-field action="copy">_icon</custom-field>
        <custom-field action="copy">_more</custom-field>
        <custom-field action="copy">_more_link</custom-field>
        <custom-field action="translate">_more_link_target</custom-field>
        <custom-field action="copy">_image_lightbox_fittoview</custom-field>

        <custom-field action="translate">_image</custom-field>
        <custom-field action="translate">_video</custom-field>
        <custom-field action="copy">_video_width</custom-field>
        <custom-field action="copy">_video_height</custom-field>
        <custom-field action="copy">_video_autoplay</custom-field>
        <custom-field action="translate">_audio</custom-field>
        <custom-field action="copy">_audio_autoplay</custom-field>
        <custom-field action="copy">_audio_loop</custom-field>
        <custom-field action="translate">_lightbox_href</custom-field>
        <custom-field action="translate">_lightbox_content</custom-field>
        <custom-field action="copy">_lightbox_width</custom-field>
        <custom-field action="copy">_lightbox_height</custom-field>
        <custom-field action="copy">_lightbox_mobile_link</custom-field>
        <custom-field action="copy">_lightbox_mobile_link_target</custom-field>
        <custom-field action="translate">_gdoc_href</custom-field>
        <custom-field action="copy">_gdoc_width</custom-field>
        <custom-field action="copy">_gdoc_height</custom-field>
        <custom-field action="translate">_gdoc_mobile_link</custom-field>
        <custom-field action="translate">_link</custom-field>
        <custom-field action="copy">_link_target</custom-field>
        <custom-field action="copy">_image_ids</custom-field>
        <custom-field action="copy">_html_image</custom-field>
        <custom-field action="copy">_html_title</custom-field>
        <custom-field action="copy">_html_more</custom-field>

        <custom-field action="copy">_product_hover</custom-field>

        <custom-field action="copy">_list_image</custom-field>
        <custom-field action="copy">_masonry_image</custom-field>
        <custom-field action="copy">_show_in_header</custom-field>
        <custom-field action="copy">_author</custom-field>
        <custom-field action="copy">_related_popular</custom-field>
    </custom-fields>
    <custom-types>
        <custom-type translate="1">portfolio</custom-type>
        <custom-type translate="1">slideshow</custom-type>
    </custom-types>    
    <taxonomies>
        <taxonomy translate="1">portfolio_category</taxonomy>
        <taxonomy translate="1">slideshow_category</taxonomy>
    </taxonomies>
    <admin-texts>
        <key name="theme_general">
            <key name="top_area_html" />
        </key>
        <key name="theme_homepage">
            <key name="page_content" />
        </key>
        <key name="theme_blog">
            <key name="read_more_text" />
        </key>
        <key name="theme_portfolio">
            <key name="permalink_slug" />
            <key name="show_text" />
            <key name="more_button_text" />
        </key>
        <key name="theme_footer">
            <key name="copyright" />
            <key name="footer_right_area_html" />
        </key>
        <key name="theme_advanced">
            <key name="nav2select_defaultText" />
            <key name="category_title" />
            <key name="category_text" />
            <key name="tag_title" />
            <key name="tag_text" />
            <key name="daily_title" />
            <key name="daily_text" />
            <key name="monthly_title" />
            <key name="monthly_text" />
            <key name="weekly_title" />
            <key name="weekly_text" />
            <key name="yearly_title" />
            <key name="yearly_text" />
            <key name="author_title" />
            <key name="author_text" />
            <key name="blog_title" />
            <key name="blog_text" />
            <key name="taxonomy_title" />
            <key name="taxonomy_text" />
            <key name="404_title" />
            <key name="404_text" />
            <key name="404_content" />
            <key name="search_title" />
            <key name="search_text" />
            <key name="search_nothing_found" />
        </key>
    </admin-texts>
</wpml-config>