{"ppb_form_data_order":["1456115282777,1466675565751"],"1456115282777_data":["{\"id\":\"1456115282777\",\"shortcode\":\"ppb_portfolio_mixed_grid\",\"ppb_portfolio_mixed_grid_title\":\"\",\"ppb_portfolio_mixed_grid_slug\":\"\",\"ppb_portfolio_mixed_grid_filterable\":\"hide\",\"ppb_portfolio_mixed_grid_cat\":\"\",\"ppb_portfolio_mixed_grid_layout\":\"wide\",\"ppb_portfolio_mixed_grid_order\":\"default\",\"ppb_portfolio_mixed_grid_items\":\"6\",\"ppb_portfolio_mixed_grid_custom_css\":\"\"}"],"1456115282777_size":["one"],"1466675565751_data":["{\"id\":\"1466675565751\",\"shortcode\":\"ppb_text_fullwidth\",\"ppb_text_fullwidth_title\":\"We%20are%20Accepting%20Projects%20Today\",\"ppb_text_fullwidth_slug\":\"\",\"ppb_text_fullwidth_padding\":\"75\",\"ppb_text_fullwidth_bgcolor\":\"#662fff\",\"ppb_text_fullwidth_fontcolor\":\"#ffffff\",\"ppb_text_fullwidth_custom_css\":\"text-align:center;\",\"ppb_text_fullwidth_content\":\"%3Ch1%20style=%22color:%20#ffffff;%22%3EWe%20are%20Accepting%20Projects%20Today%3C\/h1%3E%0A%3Cp%20style=%22margin-top:%2010px;%22%3E%3Ca%20style=%22text-transform:%20uppercase;%20color:%20#ffffff;%20letter-spacing:%203px;%20font-size:%2012px;%22%20href=%22mailto:contact@grandportfoliotheme.com%22%3Econtact@grandportfoliotheme.com%3C\/a%3E%3C\/p%3E\"}"],"1466675565751_size":["one"]}