{"ppb_form_data_order":["1450171669312,1450172230414,1450184441415,1450173142858,1450173172165,1450173172366,1450183441585,1450173405278,1450173370018,1450342327046"],"1450171669312_data":["{\"id\":\"1450171669312\",\"shortcode\":\"ppb_revslider\",\"ppb_revslider_title\":\"Slider\",\"ppb_revslider_slug\":\"\",\"ppb_revslider_slider_id\":\"home-slider\",\"ppb_revslider_display\":\"normal\"}"],"1450171669312_size":["one"],"1450172230414_data":["{\"id\":\"1450172230414\",\"shortcode\":\"ppb_header\",\"ppb_header_title\":\"We%20Are%20Musician\",\"ppb_header_slug\":\"band\",\"ppb_header_subtitle\":\"\",\"ppb_header_width\":\"70%25\",\"ppb_header_textalign\":\"center\",\"ppb_header_padding\":\"60\",\"ppb_header_bgcolor\":\"\",\"ppb_header_fontcolor\":\"\",\"ppb_header_custom_css\":\"font-size:16px;padding-bottom:%2020px%20!important;\",\"ppb_header_content\":\"%E2%80%9CSed%20ut%20perspiciatis%20unde%20omnis%20iste%20natus%20error%20sit%20voluptatem%20accusantium%20doloremque%20laudantium,%20totam%20rem%20aperiam,%20eaque%20ipsa%20%20quae%20ab%20illo%20inventore%20veritatis%20et%20quasi%20%20architecto%20beatae%20vitae%20dicta%20sunt%20explicabo.%20Nemo%20enim%20ipsam%20voluptatem%20quia%20voluptas%E2%80%9D%0A%0A\u00a0%0A%0AVocals,%20Guitar%20\/%20%3Ca%20href=%22#%22%3EMichael%20Clayton%3C\/a%3E%0AKeyboard,%20Sampling%20\/%20%3Ca%20href=%22#%22%3EJane%20Johnasson%3C\/a%3E%0ABass%20\/%20%3Ca%20href=%22#%22%3EEric%20Stone%3C\/a%3E%0ADrums%20\/%20%3Ca%20href=%22#%22%3EJohn%20Doer%3C\/a%3E\"}"],"1450172230414_size":["one"],"1450184441415_data":["{\"id\":1450184441415,\"shortcode\":\"ppb_divider\",\"ppb_text_title\":\"Paragraph Break\",\"ppb_text_content\":\"\",\"ppb_header_content\":\"\"}"],"1450184441415_size":["one"],"1450173142858_data":["{\"id\":\"1450173142858\",\"shortcode\":\"ppb_gallery_grid\",\"ppb_gallery_grid_title\":\"Band%20Gallery\",\"ppb_gallery_grid_slug\":\"\",\"ppb_gallery_grid_gallery_id\":\"27\",\"ppb_gallery_grid_layout\":\"contain\",\"ppb_gallery_grid_columns\":\"4\",\"ppb_gallery_grid_items\":\"0\"}"],"1450173142858_size":["one"],"1450173172165_data":["{\"id\":1450173172165,\"shortcode\":\"ppb_divider\",\"ppb_text_title\":\"Paragraph Break\",\"ppb_text_content\":\"\",\"ppb_header_content\":\"\"}"],"1450173172165_size":["one"],"1450173172366_data":["{\"id\":1450173172366,\"shortcode\":\"ppb_divider\",\"ppb_text_title\":\"Paragraph Break\",\"ppb_text_content\":\"\",\"ppb_header_content\":\"\"}"],"1450173172366_size":["one"],"1450183441585_data":["{\"id\":\"1450183441585\",\"shortcode\":\"ppb_portfolio_track\",\"ppb_portfolio_track_title\":\"New%20Releases\",\"ppb_portfolio_track_slug\":\"album\",\"ppb_portfolio_track_subtitle\":\"New%20Album\",\"ppb_portfolio_track_featured_image\":\"http:\/\/themes.themegoods2.com\/grandportfolio\/demo5\/wp-content\/uploads\/2015\/12\/musician.jpg\",\"ppb_portfolio_track_cat\":\"\",\"ppb_portfolio_track_order\":\"default\",\"ppb_portfolio_track_items\":\"10\",\"ppb_portfolio_track_background\":\"http:\/\/themes.themegoods2.com\/grandportfolio\/demo5\/wp-content\/uploads\/2015\/12\/photo-1416273567255-8abe875affcd-1.jpg\",\"ppb_portfolio_track_background_position\":\"center\",\"ppb_portfolio_track_fontcolor\":\"#ffffff\",\"ppb_portfolio_track_custom_css\":\"\",\"ppb_portfolio_track_content\":\"Released:%20August%2030th,%202015%20on%20Adversary%3Cbr\/%3E%0ARecords:%20Mastered%20and%20produced%20in%20New%20York.\"}"],"1450183441585_size":["one"],"1450173405278_data":["{\"id\":\"1450173405278\",\"shortcode\":\"ppb_header\",\"ppb_header_title\":\"News%20&%20Update\",\"ppb_header_slug\":\"news\",\"ppb_header_subtitle\":\"\",\"ppb_header_width\":\"100%25\",\"ppb_header_textalign\":\"center\",\"ppb_header_padding\":\"50\",\"ppb_header_bgcolor\":\"\",\"ppb_header_fontcolor\":\"\",\"ppb_header_custom_css\":\"\",\"ppb_header_content\":\"\"}"],"1450173405278_size":["one"],"1450173370018_data":["{\"id\":\"1450173370018\",\"shortcode\":\"ppb_blog_grid\",\"ppb_blog_grid_title\":\"Blog%20Grid\",\"ppb_blog_grid_slug\":\"\",\"ppb_blog_grid_cat\":\"\",\"ppb_blog_grid_columns\":\"2\",\"ppb_blog_grid_padding\":\"50\",\"ppb_blog_grid_link_title\":\"\",\"ppb_blog_grid_link_url\":\"\",\"ppb_blog_grid_items\":\"4\",\"ppb_blog_grid_items_ini\":\"0\",\"ppb_blog_grid_custom_css\":\"padding-top:0%20!important;\"}"],"1450173370018_size":["one"],"1450342327046_data":["{\"id\":\"1450342327046\",\"shortcode\":\"ppb_event_list\",\"ppb_event_list_title\":\"Our%20Tour\",\"ppb_event_list_slug\":\"tour\",\"ppb_event_list_cat\":\"\",\"ppb_event_list_items\":\"8\",\"ppb_event_list_background\":\"http:\/\/themes.themegoods2.com\/grandportfolio\/demo5\/wp-content\/uploads\/2015\/12\/photo-1442975433132-cb9580b88538.jpg\",\"ppb_event_list_background_position\":\"top\",\"ppb_event_list_fontcolor\":\"#ffffff\",\"ppb_event_list_custom_css\":\"padding-top:20px;\"}"],"1450342327046_size":["one"]}